profiled/__init__.py
profiled-2.0.0.dist-info/LICENSE
profiled-2.0.0.dist-info/METADATA
profiled-2.0.0.dist-info/WHEEL
profiled-2.0.0.dist-info/RECORD
