Metadata-Version: 2.1
Name: profiled
Version: 2.0.0
Summary: Simple profiling decorator
License: MIT
Author: Bogdan Kulynych
Author-email: bogdan@kulyny.ch
Requires-Python: >=3.10,<4.0
Classifier: License :: OSI Approved :: MIT License
Classifier: Programming Language :: Python :: 3
Classifier: Programming Language :: Python :: 3.10
Classifier: Programming Language :: Python :: 3.11
Classifier: Programming Language :: Python :: 3.12
